file_io_cli_tddschn/__init__.py
file_io_cli_tddschn/cli.py
file_io_cli_tddschn/config.py
file_io_cli_tddschn/utils.py
file_io_cli_tddschn-1.1.5.dist-info/LICENSE
file_io_cli_tddschn-1.1.5.dist-info/LICENSE.txt
file_io_cli_tddschn-1.1.5.dist-info/METADATA
file_io_cli_tddschn-1.1.5.dist-info/WHEEL
file_io_cli_tddschn-1.1.5.dist-info/entry_points.txt
file_io_cli_tddschn-1.1.5.dist-info/RECORD
