Metadata-Version: 2.1
Name: file-io-cli-tddschn
Version: 1.1.5
Summary: Command-line tool to upload files to https://file.io
Home-page: https://github.com/tddschn/file.io-cli-tddschn
License: MIT
Keywords: file.io,utility,uploader,CLI
Author: Teddy Xinyuan Chen
Author-email: 45612704+tddschn@users.noreply.github.com
Requires-Python: >=3.11,<4.0
Classifier: License :: OSI Approved :: MIT License
Classifier: Programming Language :: Python :: 3
Classifier: Programming Language :: Python :: 3.11
Classifier: Topic :: Utilities
Requires-Dist: clipboard (>=0.0.4,<1.0.0)
Requires-Dist: requests (>=2.25.1,<3.0.0)
Project-URL: Bug Tracker, https://github.com/tddschn/file.io-cli-tddschn/issues
Project-URL: Repository, https://github.com/tddschn/file.io-cli-tddschn
